vaultssh/__init__.py
vaultssh/auth.py
vaultssh/common.py
vaultssh/vaultssh.py
vaultssh-1.0.0.dist-info/LICENSE
vaultssh-1.0.0.dist-info/METADATA
vaultssh-1.0.0.dist-info/WHEEL
vaultssh-1.0.0.dist-info/entry_points.txt
vaultssh-1.0.0.dist-info/top_level.txt
vaultssh-1.0.0.dist-info/RECORD
