Metadata-Version: 2.1
Name: vaultssh
Version: 1.0.0
Summary: CLI tool for signing SSH public keys using the Vault SSH endpoint
Home-page: https://github.com/jmgilman/VaultSSH
Author: Joshua Gilman
Author-email: joshuagilman@gmail.com
License: MIT
Platform: UNKNOWN
Requires-Dist: certifi (==2019.11.28)
Requires-Dist: chardet (==3.0.4)
Requires-Dist: click (==7.0)
Requires-Dist: hvac (==0.9.6)
Requires-Dist: idna (==2.8)
Requires-Dist: requests (==2.22.0)
Requires-Dist: six (==1.14.0)
Requires-Dist: urllib3 (==1.25.8)
